setup.py
distributions_hedeya/Binomialdistribution.py
distributions_hedeya/Gaussiandistribution.py
distributions_hedeya/Generaldistribution.py
distributions_hedeya/__init__.py
distributions_hedeya.egg-info/PKG-INFO
distributions_hedeya.egg-info/SOURCES.txt
distributions_hedeya.egg-info/dependency_links.txt
distributions_hedeya.egg-info/not-zip-safe
distributions_hedeya.egg-info/top_level.txt